certbot_dns_joker/__init__.py
certbot_dns_joker/dns_joker.py
certbot_dns_joker-1.1.0.dist-info/LICENSE.txt
certbot_dns_joker-1.1.0.dist-info/METADATA
certbot_dns_joker-1.1.0.dist-info/WHEEL
certbot_dns_joker-1.1.0.dist-info/entry_points.txt
certbot_dns_joker-1.1.0.dist-info/top_level.txt
certbot_dns_joker-1.1.0.dist-info/RECORD
