Metadata-Version: 2.1
Name: certbot-dns-joker
Version: 1.1.0
Summary: Joker DNS Authenticator plugin for Certbot
Home-page: https://github.com/dhull/certbot-dns-joker
Author: David Hull
Author-email: github@davidhull.org
License: Apache 2.0
Project-URL: Issue Tracker, https://github.com/dhull/certbot-dns-joker/issues
Platform: UNKNOWN
Classifier: Development Status :: 5 - Production/Stable
Classifier: Environment :: Plugins
Classifier: Intended Audience :: System Administrators
Classifier: License :: OSI Approved :: Apache Software License
Classifier: Operating System :: POSIX :: Linux
Classifier: Programming Language :: Python
Classifier: Programming Language :: Python :: 2
Classifier: Programming Language :: Python :: 2.7
Classifier: Programming Language :: Python :: 3
Classifier: Programming Language :: Python :: 3.5
Classifier: Programming Language :: Python :: 3.6
Classifier: Programming Language :: Python :: 3.7
Classifier: Programming Language :: Python :: 3.8
Classifier: Topic :: Internet :: WWW/HTTP
Classifier: Topic :: Security
Classifier: Topic :: System :: Installation/Setup
Classifier: Topic :: System :: Networking
Classifier: Topic :: System :: Systems Administration
Classifier: Topic :: Utilities
Requires-Python: >=2.7, !=3.0.*, !=3.1.*, !=3.2.*, !=3.3.*, !=3.4.*
Requires-Dist: acme (>=0.31.0)
Requires-Dist: certbot (>=1.1.0)
Requires-Dist: requests
Requires-Dist: setuptools
Requires-Dist: zope.interface
Provides-Extra: docs
Requires-Dist: Sphinx (>=1.0) ; extra == 'docs'
Requires-Dist: sphinx-rtd-theme ; extra == 'docs'
